paperxtract/__init__.py
paperxtract/__main__.py
paperxtract/cli.py
paperxtract/extractors/__init__.py
paperxtract/extractors/openreview.py
paperxtract/formatters/__init__.py
paperxtract/formatters/text_formatter.py
paperxtract-0.1.0.dist-info/LICENSE
paperxtract-0.1.0.dist-info/METADATA
paperxtract-0.1.0.dist-info/WHEEL
paperxtract-0.1.0.dist-info/entry_points.txt
paperxtract-0.1.0.dist-info/top_level.txt
paperxtract-0.1.0.dist-info/RECORD
