Metadata-Version: 2.1
Name: paperxtract
Version: 0.1.0
Summary: Academic Paper Extraction and Formatting Tool
Home-page: https://github.com/yuxiaoLeeMarks/paperxtract
Author: yuxiaoLee
Author-email: yuxiaolee@foxmail.com
Classifier: Programming Language :: Python :: 3
Classifier: License :: OSI Approved :: MIT License
Classifier: Operating System :: OS Independent
Requires-Python: >=3.6
License-File: LICENSE
Requires-Dist: openreview-py >=1.0
Requires-Dist: pandas >=1.0.0
